brotli.py
_brotli.so
brotli-1.2.0.dist-info/LICENSE
brotli-1.2.0.dist-info/WHEEL
brotli-1.2.0.dist-info/top_level.txt
brotli-1.2.0.dist-info/METADATA
brotli-1.2.0.dist-info/RECORD
